lakera_chainguard/__init__.py
lakera_chainguard/lakera_chainguard.py
lakera_chainguard/py.typed
lakera_chainguard-0.1.6.dist-info/LICENSE
lakera_chainguard-0.1.6.dist-info/METADATA
lakera_chainguard-0.1.6.dist-info/WHEEL
lakera_chainguard-0.1.6.dist-info/RECORD
