Metadata-Version: 2.3
Name: lakera-chainguard
Version: 0.1.6
Summary: Guard your LangChain applications against prompt injection with Lakera Guard
License: MIT
Keywords: llm,langchain,prompt-injection,llm-security,lakera-guard,lakera,langchain-python
Author: Frawa Vetterli
Author-email: fv@lakera.ai
Maintainer: Lakera
Maintainer-email: opensource@lakera.ai
Requires-Python: >=3.10,<4.0
Classifier: License :: OSI Approved :: MIT License
Classifier: Programming Language :: Python :: 3
Classifier: Programming Language :: Python :: 3.10
Classifier: Programming Language :: Python :: 3.11
Classifier: Programming Language :: Python :: 3.12
Classifier: Programming Language :: Python :: 3.13
Requires-Dist: griffe (==0.49.0)
Requires-Dist: langchain (>=0.2.10,<0.3.0)
Requires-Dist: langchain-community (==0.2.5)
Requires-Dist: langchain-core (>=0.2.22,<0.3.0)
Requires-Dist: requests (>=2.31.0,<3.0.0)
Requires-Dist: types-requests (>=2.31.0.20240106,<3.0.0.0)
Project-URL: Documentation, https://lakeraai.github.io/chainguard/
Project-URL: Homepage, https://lakeraai.github.io/chainguard/
Project-URL: Repository, https://github.com/lakeraai/chainguard
